taxcalcmounica/__init__.py
taxcalcmounica/taxcalc.py
taxcalcmounica-0.1.dist-info/LICENCE
taxcalcmounica-0.1.dist-info/METADATA
taxcalcmounica-0.1.dist-info/WHEEL
taxcalcmounica-0.1.dist-info/top_level.txt
taxcalcmounica-0.1.dist-info/RECORD
