Metadata-Version: 2.1
Name: taxcalcmounica
Version: 0.1
Summary: This is tax calculator
Author: Mounica Pothureddy
Author-email: mounicapothureddy555@gmail.com
Classifier: Programming Language :: Python :: 3
Classifier: Operating System :: MacOS :: MacOS X
Classifier: Operating System :: Microsoft :: Windows
License-File: LICENCE
